wespeaker/__init__.py
wespeaker/cli/__init__.py
wespeaker/cli/hub.py
wespeaker/cli/speaker.py
wespeaker/cli/utils.py
wespeaker/diar/__init__.py
wespeaker/diar/extract_emb.py
wespeaker/diar/make_fbank.py
wespeaker/diar/make_oracle_sad.py
wespeaker/diar/make_rttm.py
wespeaker/diar/make_system_sad.py
wespeaker/diar/spectral_clusterer.py
wespeaker/diar/umap_clusterer.py
wespeaker/frontend/__init__.py
wespeaker/frontend/s3prl.py
wespeaker/frontend/whisper_encoder.py
wespeaker/models/__init__.py
wespeaker/models/campplus.py
wespeaker/models/convert_repvgg.py
wespeaker/models/ecapa_tdnn.py
wespeaker/models/eres2net.py
wespeaker/models/gemini_dfresnet.py
wespeaker/models/pooling_layers.py
wespeaker/models/projections.py
wespeaker/models/redimnet.py
wespeaker/models/repvgg.py
wespeaker/models/res2net.py
wespeaker/models/resnet.py
wespeaker/models/samresnet.py
wespeaker/models/speaker_model.py
wespeaker/models/tdnn.py
wespeaker/models/whisper_PMFA.py
wespeaker/utils/__init__.py
wespeaker/utils/checkpoint.py
wespeaker/utils/embedding_processing.py
wespeaker/utils/executor.py
wespeaker/utils/executor_deprecated.py
wespeaker/utils/file_utils.py
wespeaker/utils/schedulers.py
wespeaker/utils/score_metrics.py
wespeaker/utils/utils.py
wespeaker_unofficial-0.0.1.dist-info/LICENSE
wespeaker_unofficial-0.0.1.dist-info/METADATA
wespeaker_unofficial-0.0.1.dist-info/WHEEL
wespeaker_unofficial-0.0.1.dist-info/entry_points.txt
wespeaker_unofficial-0.0.1.dist-info/top_level.txt
wespeaker_unofficial-0.0.1.dist-info/RECORD
