Metadata-Version: 2.1
Name: wespeaker-unofficial
Version: 0.0.1
Summary: Unofficial wespeaker pypi package
License: Apache Software License
Classifier: License :: OSI Approved :: Apache Software License
Classifier: Operating System :: OS Independent
Classifier: Programming Language :: Python :: 3
Requires-Python: >=3.8
License-File: LICENSE
Requires-Dist: tqdm
Requires-Dist: kaldiio
Requires-Dist: hdbscan ==0.8.37
Requires-Dist: umap-learn ==0.5.6
Requires-Dist: torch >=1.12.0
Requires-Dist: torchaudio >=0.12.0
Requires-Dist: silero-vad
